<?xml version="1.0" encoding="utf-8" ?>
<Defs>

<AlienRace.BackstoryDef>
    <defName>FennexAgentKid</defName>
    <title>Young agent</title>
	<titleShort>Kid-agent</titleShort>
    <baseDescription>[PAWN_nameDef] was born in one of the training facilities devoted to producing intelligence operatives. [PAWN_possessive] formative years were occupied with many of the usual mundane types of education, but augmented with courses on observation and combat.</baseDescription>
    <slot>Childhood</slot>
	<bodyTypeFemale>Female</bodyTypeFemale>
	<bodyTypeMale>Male</bodyTypeMale>
	<bodyTypeGlobal>Thin</bodyTypeGlobal>
	<maleCommonality>20</maleCommonality>
	<femaleCommonality>20</femaleCommonality>
    <spawnCategories>
      <li>FennexBackstory</li>
    </spawnCategories>
    <skillGains>
      <li>
        <defName>Social</defName>
        <amount>2</amount>
      </li>
	   <li>
        <defName>Melee</defName>
        <amount>4</amount>
      </li>
      <li>
        <defName>Shooting</defName>
        <amount>4</amount>
      </li>
	    <li>
        <defName>Plants</defName>
        <amount>4</amount>
      </li>
    </skillGains>
</AlienRace.BackstoryDef>


<AlienRace.BackstoryDef>
    <defName>FennexMisckid</defName>
    <title>Mischevious</title>
	<titleShort>Mischevious</titleShort>
    <baseDescription>[PAWN_nameDef] was the classic mischevious kit. Always getting caught with [PAWN_possessive] hands in the cookie jar (literal or proverbial).</baseDescription>
    <slot>Childhood</slot>
	<bodyTypeFemale>Female</bodyTypeFemale>
	<bodyTypeMale>Male</bodyTypeMale>
	<maleCommonality>20</maleCommonality>
	<femaleCommonality>20</femaleCommonality>
    <spawnCategories>
      <li>FennexBackstory</li>
    </spawnCategories>
    <skillGains>
      <li>
        <defName>Construction</defName>
        <amount>2</amount>
      </li>
	    <li>
        <defName>Melee</defName>
        <amount>4</amount>
      </li>
	   <li>
        <defName>Plants</defName>
        <amount>2</amount>
      </li>
      <li>
       <defName>Social</defName>
        <amount>3</amount>
      </li>
    </skillGains>
</AlienRace.BackstoryDef>


<AlienRace.BackstoryDef>
    <defName>FennexMEng</defName>
    <title>Mech engineer</title>
	<titleShort>M-Engineer</titleShort>
    <baseDescription>[PAWN_nameDef] was a technician working on bipedal walking battlemechs in the Solaris arena. [PAWN_possessive] long hours kept [PAWN_possessive] team winning matches, and honed [PAWN_possessive] skills to a razor edge.</baseDescription>
    <slot>Adulthood</slot>
    <spawnCategories>
      <li>FennexBackstory</li>
    </spawnCategories>
	<bodyTypeFemale>Female</bodyTypeFemale>
	<bodyTypeMale>Male</bodyTypeMale>
	<bodyTypeGlobal>Thin</bodyTypeGlobal>
		<maleCommonality>20</maleCommonality>
	<femaleCommonality>20</femaleCommonality>
    <skillGains>
      <li>
        <defName>Construction</defName>
        <amount>6</amount>
      </li>
	        <li>
        <defName>Crafting</defName>
        <amount>6</amount>
      </li>
      <li>
        <defName>Plants</defName>
        <amount>4</amount>
      </li>
    </skillGains>
</AlienRace.BackstoryDef>

<AlienRace.BackstoryDef>
    <defName>FennexMachinW</defName>
    <title>Machinist</title>
	<titleShort>Machinist</titleShort>
    <baseDescription>[PAWN_nameDef] worked in a metal shop, working a metal milling machine, manufacturing components for various devices. [PAWN_pronoun] has a fine eye for detail, and a steady hand.</baseDescription>
    <slot>Adulthood</slot>
    <spawnCategories>
      <li>FennexBackstory</li>
    </spawnCategories>
	<bodyTypeFemale>Female</bodyTypeFemale>
	<bodyTypeMale>Male</bodyTypeMale>
	<bodyTypeGlobal>Thin</bodyTypeGlobal>
		<maleCommonality>20</maleCommonality>
	<femaleCommonality>20</femaleCommonality>
    <skillGains>
      <li>
        <defName>Construction</defName>
        <amount>3</amount>
      </li>
	        <li>
        <defName>Crafting</defName>
        <amount>7</amount>
      </li>
    </skillGains>
</AlienRace.BackstoryDef>

<AlienRace.BackstoryDef>
    <defName>FennexEngineerX</defName>
    <title>Hotrod apprentice</title>
	<titleShort>Hot-rodder</titleShort>
    <baseDescription>[PAWN_nameDef] worked with [PAWN_possessive] father, running an old Auto-repair shop in a dusty frontier town, restoring old wrecks into dream-machines. How [PAWN_pronoun] ended up here is a mystery...</baseDescription>
    <slot>Childhood</slot>
    <spawnCategories>
      <li>FennexBackstory</li>
    </spawnCategories>
	<bodyTypeFemale>Female</bodyTypeFemale>
	<bodyTypeMale>Male</bodyTypeMale>
	<bodyTypeGlobal>Thin</bodyTypeGlobal>
		<maleCommonality>20</maleCommonality>
	<femaleCommonality>20</femaleCommonality>
    <skillGains>
      <li>
        <defName>Intellectual</defName>
        <amount>6</amount>
      </li>
	        <li>
        <defName>Crafting</defName>
        <amount>5</amount>
      </li>
    </skillGains>
</AlienRace.BackstoryDef>

<AlienRace.BackstoryDef>
    <defName>FennexOrchard</defName>
    <title>Fruit rancher</title>
	<titleShort>F-Rancher</titleShort>
    <baseDescription>[PAWN_nameDef] had fine orchards, with the juiciest Oranges around... until a strange meteorite landed square in the middle of [PAWN_possessive] land, tainting the soil. It's only a matter of time tile [PAWN_pronoun] can get on [PAWN_possessive] feet again.</baseDescription>
    <slot>Adulthood</slot>
    <spawnCategories>
      <li>FennexBackstory</li>
    </spawnCategories>
	<bodyTypeFemale>Female</bodyTypeFemale>
	<bodyTypeMale>Male</bodyTypeMale>
	<bodyTypeGlobal>Thin</bodyTypeGlobal>
		<maleCommonality>20</maleCommonality>
	<femaleCommonality>20</femaleCommonality>
    <skillGains>
      <li>
        <defName>Plants</defName>
        <amount>6</amount>
      </li>
	   <li>
        <defName>Crafting</defName>
        <amount>6</amount>
      </li>
	  	   <li>
        <defName>Medicine</defName>
        <amount>3</amount>
      </li>
      <li>
        <defName>Shooting</defName>
        <amount>4</amount>
      </li>
    </skillGains>
</AlienRace.BackstoryDef>

<AlienRace.BackstoryDef>
    <defName>FennexTyrokid</defName>
    <title>Tyro</title>
	<titleShort>Tyro</titleShort>
    <baseDescription>[PAWN_nameDef] was apprenticing under [PAWN_possessive] father, learning the family trade. [PAWN_pronoun] was an attentive student, but always longed for [PAWN_possessive] free time when HE would play with [PAWN_possessive] B-B gun in the fields near [PAWN_possessive] home.</baseDescription>
    <slot>Childhood</slot>
    <spawnCategories>
      <li>FennexBackstory</li>
    </spawnCategories>
	<bodyTypeFemale>Female</bodyTypeFemale>
	<bodyTypeMale>Male</bodyTypeMale>
	<bodyTypeGlobal>Thin</bodyTypeGlobal>
		<maleCommonality>20</maleCommonality>
	<femaleCommonality>20</femaleCommonality>
    <skillGains>
      <li>
        <defName>Intellectual</defName>
        <amount>3</amount>
      </li>
	        <li>
        <defName>Crafting</defName>
        <amount>3</amount>
      </li>
      <li>
        <defName>Shooting</defName>
        <amount>4</amount>
      </li>
      <li>
        <defName>Social</defName>
        <amount>3</amount>
      </li>
    </skillGains>
</AlienRace.BackstoryDef>

    <AlienRace.BackstoryDef>
    <defName>FennexSpacer</defName>
    <title>Noble line</title>
    <titleShort>Noble</titleShort>
    <baseDescription>[PAWN_nameDef] is apparently descended from an ancient line of kings, or at least [PAWN_possessive] grandfather was always drumming it into [PAWN_possessive] head, along with various lessons on etiquette, protocol, and political lessons.</baseDescription>
    <slot>Childhood</slot>
	  <bodyTypeFemale>Female</bodyTypeFemale>
  	<bodyTypeMale>Male</bodyTypeMale>
		<maleCommonality>30</maleCommonality>
	  <femaleCommonality>30</femaleCommonality>
      <spawnCategories>
      <li>FennexBackstory</li>
    </spawnCategories>
    <skillGains>
          <li>
        <defName>Construction</defName>
        <amount>6</amount>
      </li>
      <li>
        <defName>Social</defName>
        <amount>6</amount>
      </li>
      <li>
        <defName>Crafting</defName>
        <amount>3</amount>
      </li>
    </skillGains>
    </AlienRace.BackstoryDef>

	    <AlienRace.BackstoryDef>
    <defName>FennexForestKid</defName>
    <title>Young forester</title>
    <titleShort>Forester-kid</titleShort>
    <baseDescription>[PAWN_nameDef] grew up right at the edge of a great forest. [PAWN_pronoun] spent most of [PAWN_possessive] free time playing and investigating all the fascinating plants and animals that [PAWN_pronoun] could find there.</baseDescription>
    <slot>Childhood</slot>
    <bodyTypeMale>Male</bodyTypeMale>
    <bodyTypeFemale>Female</bodyTypeFemale>
		<maleCommonality>20</maleCommonality>
  	<femaleCommonality>20</femaleCommonality>
      <spawnCategories>
      <li>FennexBackstory</li>
    </spawnCategories>
    <skillGains>
          <li>
        <defName>Plants</defName>
        <amount>6</amount>
      </li>
      <li>
        <defName>Shooting</defName>
        <amount>4</amount>
      </li>
      <li>
        <defName>Construction</defName>
        <amount>4</amount>
      </li>
        <li>
        <defName>Crafting</defName>
        <amount>2</amount>
      </li>
    </skillGains>
	   <workDisables>
        <li>Firefighting</li>
	   </workDisables>
    </AlienRace.BackstoryDef>


    <AlienRace.BackstoryDef>
    <defName>FennexColonyKid</defName>
    <title>Fennex colonykid</title>
    <titleShort>Kid</titleShort>
    <baseDescription>[PAWN_nameDef] was born in a small trading post on the outer rims. [PAWN_pronoun] had to learn to carry [PAWN_possessive] weight and keep the colony running from an early age.</baseDescription>
    <slot>Childhood</slot>
	<bodyTypeFemale>Female</bodyTypeFemale>
	<bodyTypeMale>Male</bodyTypeMale>
	<bodyTypeGlobal>Thin</bodyTypeGlobal>
		<maleCommonality>80</maleCommonality>
	<femaleCommonality>80</femaleCommonality>
    <skillGains>
      <li>
        <defName>Social</defName>
        <amount>2</amount>
      </li>
      <li>
        <defName>Construction</defName>
        <amount>1</amount>
      </li>
      <li>
        <defName>Plants</defName>
        <amount>2</amount>
      </li>
    </skillGains>
    <spawnCategories>
      <li>FennexBackstory</li>
    </spawnCategories>
  </AlienRace.BackstoryDef>


  <AlienRace.BackstoryDef>
    <defName>FennexCityKid</defName>
    <title>City kid</title>
    <titleShort>Urb-kit</titleShort>
    <baseDescription>[PAWN_nameDef] grew up in one of the megalopolis centers on a dense Urbworld. After school, [PAWN_pronoun] would head off to one of the metro malls or arcades. Growing up in a concrete landscape, left [PAWN_pronoun] a bit lacking when it comes to plants and animals.</baseDescription>
    <slot>Childhood</slot>
	<bodyTypeFemale>Female</bodyTypeFemale>
	<bodyTypeMale>Male</bodyTypeMale>
	<maleCommonality>80</maleCommonality>
	<femaleCommonality>80</femaleCommonality>
    <skillGains>
          <li>
        <defName>Shooting</defName>
        <amount>4</amount>
      </li>
      <li>
        <defName>Social</defName>
        <amount>4</amount>
      </li>
      <li>
        <defName>Construction</defName>
        <amount>2</amount>
      </li>
      <li>
        <defName>Plants</defName>
        <amount>-1</amount>
      </li>
    </skillGains>
    <spawnCategories>
      <li>FennexBackstory</li>
    </spawnCategories>
  </AlienRace.BackstoryDef>

  <AlienRace.BackstoryDef>
    <defName>FennexCountryKid</defName>
    <title>Farm kid</title>
    <titleShort>Farm-kit</titleShort>
    <baseDescription>[PAWN_nameDef] grew up in an ag region, supporting the major metropolises food supply on [PAWN_possessive] Rimworld. Living so far from other young people made social life difficult, but [PAWN_nameDef] made the best of it - though [PAWN_pronoun] ended up a bit shy.</baseDescription>
    <slot>Childhood</slot>
	<bodyTypeFemale>Female</bodyTypeFemale>
	<bodyTypeMale>Male</bodyTypeMale>
	<maleCommonality>80</maleCommonality>
	<femaleCommonality>80</femaleCommonality>
    <skillGains>
          <li>
        <defName>Shooting</defName>
        <amount>4</amount>
      </li>
      <li>
        <defName>Social</defName>
        <amount>-2</amount>
      </li>
      <li>
        <defName>Construction</defName>
        <amount>2</amount>
      </li>
      <li>
        <defName>Plants</defName>
        <amount>5</amount>
      </li>
    </skillGains>
    <spawnCategories>
      <li>FennexBackstory</li>
    </spawnCategories>
  </AlienRace.BackstoryDef>

  <AlienRace.BackstoryDef>
    <defName>FennexGeniusKid</defName>
    <title>Young genius</title>
    <titleShort>Prodigy</titleShort>
    <baseDescription>[PAWN_nameDef] loved tinkering with [PAWN_possessive] toys, taking them apart and reassembling them - programming simple little computer programs from [PAWN_possessive] elementary school textbooks - or simply reading any piece of information [PAWN_pronoun] can get [PAWN_possessive] hands on.</baseDescription>
    <slot>Childhood</slot>
	<bodyTypeFemale>Female</bodyTypeFemale>
	<bodyTypeMale>Male</bodyTypeMale>
	<maleCommonality>80</maleCommonality>
	<femaleCommonality>80</femaleCommonality>
    <skillGains>
          <li>
        <defName>Shooting</defName>
        <amount>4</amount>
      </li>
      <li>
        <defName>Social</defName>
        <amount>2</amount>
      </li>
      <li>
        <defName>Construction</defName>
        <amount>4</amount>
      </li>
      <li>
        <defName>Plants</defName>
        <amount>5</amount>
      </li>
         <li>
        <defName>Intellectual</defName>
        <amount>6</amount>
      </li>
    </skillGains>
    <spawnCategories>
      <li>FennexBackstory</li>
    </spawnCategories>
  </AlienRace.BackstoryDef>

   <AlienRace.BackstoryDef>
    <defName>FennexDigKid</defName>
    <title>Tunnel kit</title>
    <titleShort>T-kit</titleShort>
    <baseDescription>[PAWN_nameDef] was always digging little tunnels in the dirt or snow, or making sandcastles at the beach. [PAWN_possessive] parents encouraged [PAWN_pronoun] to learn about geology, and [PAWN_possessive] father would challenge [PAWN_pronoun] to find certain kinds of rocks in the yard.</baseDescription>
	  <bodyTypeMale>Male</bodyTypeMale>
    <bodyTypeFemale>Female</bodyTypeFemale>
    <maleCommonality>20</maleCommonality>
	  <femaleCommonality>20</femaleCommonality>
	<slot>Childhood</slot>
    <skillGains>
      <li>
        <defName>Plants</defName>
        <amount>4</amount>
      </li>
	  <li>
        <defName>Mining</defName>
        <amount>4</amount>
      </li>
    </skillGains>
    <spawnCategories>
      <li>FennexBackstory</li>
    </spawnCategories>
  </AlienRace.BackstoryDef>


  <!-- ====== Adult Stories - not porn ====== -->



    <AlienRace.BackstoryDef>
    <defName>FennexArmorer</defName>
    <title>Armorer</title>
    <titleShort>Armorer</titleShort>
    <baseDescription>[PAWN_nameDef] was interested in guns and firearms of all kinds from a young age. [PAWN_possessive] interest led [PAWN_pronoun] to the military, where he was in charge of the Armory - maintiaing all the weapons and various equipment alongside the Gunsmiths.</baseDescription>
    <bodyTypeMale>Male</bodyTypeMale>
    <bodyTypeFemale>Female</bodyTypeFemale>
		<maleCommonality>20</maleCommonality>
	<femaleCommonality>20</femaleCommonality>
    <slot>Adulthood</slot>
    <skillGains>
      <li>
        <defName>Shooting</defName>
        <amount>5</amount>
      </li>
      <li>
        <defName>Crafting</defName>
        <amount>9</amount>
      </li>
    </skillGains>
    <spawnCategories>
      <li>FennexBackstory</li>
    </spawnCategories>
  </AlienRace.BackstoryDef>

      <AlienRace.BackstoryDef>
    <defName>FennexProst</defName>
    <title>Hooker</title>
    <titleShort>Hooker</titleShort>
    <baseDescription>[PAWN_nameDef] was a practitioner of 'the oldest profession' - walking the streets selling ass.</baseDescription>
    <bodyTypeMale>Male</bodyTypeMale>
    <bodyTypeFemale>Female</bodyTypeFemale>
		<maleCommonality>10</maleCommonality>
  	<femaleCommonality>20</femaleCommonality>
    <slot>Adulthood</slot>
    <workDisables>
     <li>Hauling</li>
	   <li>Cleaning</li>
    </workDisables>
    <skillGains>
      <li>
        <defName>Social</defName>
        <amount>5</amount>
        </li>
	     <li>
        <defName>Plants</defName>
        <amount>4</amount>
      </li>
    </skillGains>
    <spawnCategories>
      <li>FennexBackstory</li>
    </spawnCategories>
  </AlienRace.BackstoryDef>

      <AlienRace.BackstoryDef>
    <defName>Fennexminer</defName>
    <title>Deep-tunnel miner</title>
    <titleShort>Deepminer</titleShort>
    <baseDescription>[PAWN_nameDef] operated a deep-core drilling rig, sometimes miles below the surface where the stresses from pressure and heat on the machines require constant maintenance. [PAWN_pronoun] developed a strong back and keen eye for geology and metallurgy.</baseDescription>
    <bodyTypeMale>Male</bodyTypeMale>
    <bodyTypeFemale>Female</bodyTypeFemale>
		<maleCommonality>30</maleCommonality>
	<femaleCommonality>20</femaleCommonality>
    <slot>Adulthood</slot>
    <skillGains>
      <li>
        <defName>Shooting</defName>
        <amount>3</amount>
      </li>
      <li>
        <defName>Mining</defName>
        <amount>6</amount>
      </li>
    </skillGains>
    <spawnCategories>
      <li>FennexBackstory</li>
    </spawnCategories>
  </AlienRace.BackstoryDef>

    <AlienRace.BackstoryDef>
    <defName>FennexBiogen</defName>
    <title>Biologist</title>
    <titleShort>Biologist</titleShort>
    <baseDescription>[PAWN_nameDef] is a biologist. [PAWN_pronoun] has dedicated [PAWN_possessive] life to unravelling the secrets of life itself! Or just studying it, depending on your specific field!</baseDescription>
    <bodyTypeGlobal>Thin</bodyTypeGlobal>
		<maleCommonality>20</maleCommonality>
	<femaleCommonality>20</femaleCommonality>
    <slot>Adulthood</slot>
    <skillGains>
      <li>
        <defName>Intellectual</defName>
        <amount>6</amount>
      </li>
      <li>
        <defName>Crafting</defName>
        <amount>5</amount>
      </li>
    </skillGains>
    <spawnCategories>
      <li>FennexBackstory</li>
    </spawnCategories>
  </AlienRace.BackstoryDef>

  
    <AlienRace.BackstoryDef>
    <defName>FennexConn</defName>
    <title>Restaurateur</title>
    <titleShort>Restaurateur</titleShort>
    <baseDescription>[PAWN_nameDef] owned and operated a chain of successful high-class urbworld restaurants. Unfortunately, they didn't survive the franchise wars against Taco Gong, and [PAWN_pronoun] was forced to flee the planet.</baseDescription>
  	<bodyTypeMale>Male</bodyTypeMale>
    <bodyTypeFemale>Female</bodyTypeFemale>
    <bodyTypeGlobal>Fat</bodyTypeGlobal>
  <maleCommonality>20</maleCommonality>
	<femaleCommonality>20</femaleCommonality>
    <slot>Adulthood</slot>
    <skillGains>
      <li>
        <defName>Cooking</defName>
        <amount>6</amount>
      </li>
      <li>
        <defName>Intellectual</defName>
        <amount>5</amount>
      </li>
    </skillGains>
    <spawnCategories>
      <li>FennexBackstory</li>
    </spawnCategories>
  </AlienRace.BackstoryDef>

    <AlienRace.BackstoryDef>
    <defName>FennexStalkerBS</defName>
    <title>Fennex hunter</title>
    <titleShort>Hunter</titleShort>
    <baseDescription>[PAWN_nameDef] is a professional hunter. Sometimes called to put down manhunters, or guide rich dentists on Safari, [PAWN_possessive] skills as a tracker are only matched by [PAWN_possessive] skill at handling.</baseDescription>
    <bodyTypeMale>Male</bodyTypeMale>
    <bodyTypeFemale>Female</bodyTypeFemale>
		<maleCommonality>25</maleCommonality>
	<femaleCommonality>25</femaleCommonality>
    <slot>Adulthood</slot>
    <skillGains>
      <li>
        <defName>Animals</defName>
        <amount>6</amount>
      </li>
      <li>
        <defName>Social</defName>
        <amount>2</amount>
      </li>
	  <li>
        <defName>Shooting</defName>
        <amount>2</amount>
      </li>
    </skillGains>
    <spawnCategories>
      <li>FennexBackstory</li>
    </spawnCategories>
  </AlienRace.BackstoryDef>


  <AlienRace.BackstoryDef>
    <defName>FennexDistiller</defName>
    <title>Booze king</title>
    <titleShort>Distiller</titleShort>
    <baseDescription>[PAWN_nameDef] was renowned for making the strongest liquors. If you wanted a drink that would put down a raging Thrumbo, [PAWN_pronoun] had the stuff. Unfortunately, a leak in a storage tank plus a small spark equals a very large explosion and 'no more distillery'. Looks like [PAWN_pronoun] is starting over...</baseDescription>
    <bodyTypeMale>Male</bodyTypeMale>
    <bodyTypeFemale>Female</bodyTypeFemale>
		<maleCommonality>20</maleCommonality>
	<femaleCommonality>20</femaleCommonality>
    <slot>Adulthood</slot>
    <skillGains>
      <li>
        <defName>Crafting</defName>
        <amount>6</amount>
      </li>
      <li>
        <defName>Plants</defName>
        <amount>4</amount>
      </li>
    </skillGains>
    <spawnCategories>
      <li>FennexBackstory</li>
    </spawnCategories>
  </AlienRace.BackstoryDef>

    <AlienRace.BackstoryDef>
    <defName>FennexTrailblazer</defName>
    <title>Trail blazer</title>
    <titleShort>Blazer</titleShort>
    <baseDescription>[PAWN_nameDef] is at the forefront of the effort to expand the territories controlled by the Alliance - rushing headlong into the unknown to colonize uncharted worlds and eke out a living.</baseDescription>
    <bodyTypeMale>Male</bodyTypeMale>
    <bodyTypeFemale>Female</bodyTypeFemale>
		<maleCommonality>30</maleCommonality>
	<femaleCommonality>30</femaleCommonality>
    <slot>Adulthood</slot>
    <skillGains>
      <li>
        <defName>Melee</defName>
        <amount>3</amount>
      </li>
      <li>
        <defName>Plants</defName>
        <amount>3</amount>
      </li>
      <li>
        <defName>Construction</defName>
        <amount>3</amount>
      </li>
    </skillGains>
    <spawnCategories>
      <li>FennexBackstory</li>
    </spawnCategories>
  </AlienRace.BackstoryDef>


     <AlienRace.BackstoryDef>
    <defName>FennexResearcher</defName>
    <title>Historical researcher</title>
    <titleShort>Researcher</titleShort>
    <baseDescription>[PAWN_nameDef] is among the foremost historians among [PAWN_possessive] people, especially in regards to lineage and ancient heraldry. Many have sought [PAWN_possessive] services, claiming relation to some long-dead king or emperor. [PAWN_pronoun] delves through ancient texts and records in search of what truth can be found.</baseDescription>
    <bodyTypeMale>Male</bodyTypeMale>
    <bodyTypeFemale>Female</bodyTypeFemale>
		<maleCommonality>20</maleCommonality>
	<femaleCommonality>20</femaleCommonality>
    <slot>Adulthood</slot>
    <skillGains>
      <li>
        <defName>Intellectual</defName>
        <amount>7</amount>
      </li>
      <li>
        <defName>Artistic</defName>
        <amount>3</amount>
      </li>
      <li>
        <defName>Shooting</defName>
        <amount>3</amount>
      </li>
    </skillGains>
    <spawnCategories>
      <li>FennexBackstory</li>
    </spawnCategories>
  </AlienRace.BackstoryDef>

  <AlienRace.BackstoryDef>
    <defName>FennexDoctor</defName>
    <title>Frontier doctor</title>
    <titleShort>Doc</titleShort>
    <baseDescription>[PAWN_nameDef] has taken an oath to devote [PAWN_possessive] life to healing others. [PAWN_pronoun] has taken [PAWN_possessive] mission out to the furthest reaches and the dustiest outposts. You know... places like this...</baseDescription>
    <bodyTypeMale>Male</bodyTypeMale>
    <bodyTypeFemale>Female</bodyTypeFemale>
		<maleCommonality>25</maleCommonality>
	<femaleCommonality>25</femaleCommonality>
    <slot>Adulthood</slot>
    <skillGains>
      <li>
        <defName>Medicine</defName>
        <amount>8</amount>
      </li>
    </skillGains>
    <spawnCategories>
	 <li>FennexBackstory</li>
    </spawnCategories>
  </AlienRace.BackstoryDef>

    <AlienRace.BackstoryDef>
    <defName>FennexChef</defName>
    <title>Fennex diner-chef</title>
    <titleShort>Diner-chef</titleShort>
    <baseDescription>[PAWN_nameDef] was a chef in an old Retro-style diner from ancient earth history. It was a pretty popular place, the cherry-red seating and chrome hilights flash and splendor matched the fantastically prepared diner-style food [PAWN_pronoun] created every day. How did [PAWN_pronoun] end up here?</baseDescription>
		<bodyTypeMale>Male</bodyTypeMale>
    <bodyTypeFemale>Female</bodyTypeFemale>
    <maleCommonality>30</maleCommonality>
	<femaleCommonality>30</femaleCommonality>
    <slot>Adulthood</slot>
    <skillGains>
      <li>
        <defName>Cooking</defName>
        <amount>8</amount>
      </li>
    </skillGains>
    <spawnCategories>
	 <li>FennexBackstory</li>
    </spawnCategories>
  </AlienRace.BackstoryDef>

  <AlienRace.BackstoryDef>
    <defName>FennexKeeper</defName>
    <title>Fennex librarian</title>
    <titleShort>Keeper</titleShort>
    <baseDescription>[PAWN_nameDef] spent [PAWN_possessive] days sorting, stacking, and reading, books of all kinds, as a Keeper in one of the central city libraries.</baseDescription>
    <bodyTypeMale>Male</bodyTypeMale>
    <bodyTypeFemale>Female</bodyTypeFemale>
		<maleCommonality>20</maleCommonality>
	<femaleCommonality>20</femaleCommonality>
    <slot>Adulthood</slot>
    <skillGains>
      <li>
        <defName>Medicine</defName>
        <amount>4</amount>
      </li>
	  <li>
        <defName>Construction</defName>
        <amount>3</amount>
      </li>
	  <li>
        <defName>Intellectual</defName>
        <amount>6</amount>
      </li>
    </skillGains>
    <spawnCategories>
	 <li>FennexBackstory</li>
    </spawnCategories>
  </AlienRace.BackstoryDef>

  <AlienRace.BackstoryDef>
    <defName>PrivateFennex</defName>
    <title>Runner</title>
    <titleShort>Runner</titleShort>
    <baseDescription>[PAWN_nameDef] was a package runner for a small delivery service. It is [PAWN_possessive] duty to deliver small items and packages, or information, wherever [PAWN_possessive] superiors order.</baseDescription>
    <bodyTypeMale>Male</bodyTypeMale>
    <bodyTypeFemale>Female</bodyTypeFemale>
		<maleCommonality>30</maleCommonality>
	<femaleCommonality>30</femaleCommonality>
    <slot>Adulthood</slot>
    <skillGains>
      <li>
        <defName>Shooting</defName>
        <amount>5</amount>
      </li>
      <li>
        <defName>Melee</defName>
        <amount>5</amount>
      </li>
    </skillGains>
    <spawnCategories>
      <li>FennexBackstory</li>
    </spawnCategories>
  </AlienRace.BackstoryDef>

    <AlienRace.BackstoryDef>
    <defName>MajorFennex</defName>
    <title>Tank commander</title>
    <titleShort>T-Commander</titleShort>
    <baseDescription>[PAWN_nameDef] was commanding officer of an armored assault unit. [PAWN_pronoun] has endured heavy military and tactical training, with a heavy focus on armored vehicle combat.</baseDescription>
    <bodyTypeMale>Male</bodyTypeMale>
    <bodyTypeFemale>Female</bodyTypeFemale>
		<maleCommonality>20</maleCommonality>
	<femaleCommonality>20</femaleCommonality>
    <slot>Adulthood</slot>
    <skillGains>
      <li>
        <defName>Shooting</defName>
        <amount>6</amount>
      </li>
      <li>
        <defName>Melee</defName>
        <amount>6</amount>
      </li>
       <li>
        <defName>Social</defName>
        <amount>4</amount>
      </li>
    </skillGains>
    <spawnCategories>
      <li>FennexBackstory</li>
    </spawnCategories>
  </AlienRace.BackstoryDef>

    <AlienRace.BackstoryDef>
    <defName>FennexSpacerAdult</defName>
    <title>Fennex space-trader</title>
    <titleShort>F-Spacer</titleShort>
    <baseDescription>[PAWN_nameDef] was a free-trader, roving the tradeways searching for deals and opportunities for profit. Until now, HE was flying a ship, making deals with colonies like these... I wonder what happened?</baseDescription>
    <slot>Adulthood</slot>
    <bodyTypeMale>Male</bodyTypeMale>
    <bodyTypeFemale>Female</bodyTypeFemale>
	    <bodyTypeGlobal>Thin</bodyTypeGlobal>
			<maleCommonality>30</maleCommonality>
	<femaleCommonality>30</femaleCommonality>
      <spawnCategories>
      <li>FennexBackstory</li>
    </spawnCategories>
    <skillGains>
          <li>
        <defName>Melee</defName>
        <amount>6</amount>
      </li>
      <li>
        <defName>Social</defName>
        <amount>10</amount>
      </li>
      <li>
        <defName>Shooting</defName>
        <amount>2</amount>
      </li>
    </skillGains>
    </AlienRace.BackstoryDef>

	  <AlienRace.BackstoryDef>
    <defName>FennexTroop</defName>
    <title>Fox-hound</title>
    <titleShort>Foxhound</titleShort>
    <baseDescription>[PAWN_nameDef] was one of an ultra-elite troop of soldiers, founded by the legendary "Really Big Boss". </baseDescription>
    <bodyTypeMale>Male</bodyTypeMale>
    <bodyTypeFemale>Female</bodyTypeFemale>
		<maleCommonality>28</maleCommonality>
	<femaleCommonality>28</femaleCommonality>
    <slot>Adulthood</slot>
    <skillGains>
      <li>
        <defName>Melee</defName>
        <amount>6</amount>
      </li>
      <li>
        <defName>Shooting</defName>
        <amount>6</amount>
      </li>
      <li>
        <defName>Medicine</defName>
        <amount>4</amount>
      </li>
	  <li>
        <defName>Crafting</defName>
        <amount>4</amount>
      </li>
    </skillGains>
    <spawnCategories>
      <li>FennexBackstory</li>
    </spawnCategories>
  </AlienRace.BackstoryDef>

    <AlienRace.BackstoryDef>
    <defName>FennexAssassin</defName>
    <title>Fennex hitman</title>
    <titleShort>Cleaner</titleShort>
    <baseDescription>[PAWN_nameDef] is a deadly assassin for profit. [PAWN_pronoun] always completes [PAWN_possessive] contracts (and always tries to look REALLY cool while doing it).</baseDescription>
    <bodyTypeMale>Male</bodyTypeMale>
    <bodyTypeFemale>Female</bodyTypeFemale>
		<maleCommonality>28</maleCommonality>
  	<femaleCommonality>28</femaleCommonality>
    <slot>Adulthood</slot>
    <skillGains>
      <li>
        <defName>Melee</defName>
        <amount>6</amount>
      </li>
      <li>
        <defName>Shooting</defName>
        <amount>6</amount>
      </li>
      <li>
        <defName>Medicine</defName>
        <amount>4</amount>
      </li>
	    <li>
        <defName>Crafting</defName>
        <amount>4</amount>
      </li>
    </skillGains>
    <spawnCategories>
      <li>FennexBackstory</li>
    </spawnCategories>
  </AlienRace.BackstoryDef>


  	  <AlienRace.BackstoryDef>
    <defName>FennexAstroPhy</defName>
    <title>Astryphysicist</title>
    <titleShort>Astrophysicist</titleShort>
    <baseDescription>[PAWN_nameDef] was inspired from childhood by the stars. [PAWN_pronoun] spent many long hours gazing through [PAWN_possessive] telescope, charting the cosmos.</baseDescription>
    <bodyTypeMale>Male</bodyTypeMale>
    <bodyTypeFemale>Female</bodyTypeFemale>
		<maleCommonality>10</maleCommonality>
	<femaleCommonality>10</femaleCommonality>
    <slot>Adulthood</slot>
    <skillGains>
      <li>
        <defName>Melee</defName>
        <amount>6</amount>
      </li>
      <li>
        <defName>Shooting</defName>
        <amount>9</amount>
      </li>
      <li>
        <defName>Social</defName>
        <amount>1</amount>
      </li>
	  <li>
        <defName>Crafting</defName>
        <amount>4</amount>
      </li>
    </skillGains>
    <spawnCategories>
      <li>FennexBackstory</li>
    </spawnCategories>
  </AlienRace.BackstoryDef>

  	  <AlienRace.BackstoryDef>
    <defName>FennexAgentBS</defName>
    <title>Paleobotanist</title>
    <titleShort>Paleobotanist</titleShort>
    <baseDescription>[PAWN_nameDef] has spent years studying ancient plant life, excavating and preserving ancient specimens from geological substrates, or studying samples in the lab.</baseDescription>
    <bodyTypeMale>Male</bodyTypeMale>
    <bodyTypeFemale>Female</bodyTypeFemale>
		<maleCommonality>10</maleCommonality>
	<femaleCommonality>10</femaleCommonality>
    <slot>Adulthood</slot>
    <skillGains>
      <li>
        <defName>Melee</defName>
        <amount>6</amount>
      </li>
      <li>
        <defName>Shooting</defName>
        <amount>6</amount>
      </li>
      <li>
        <defName>Medicine</defName>
        <amount>4</amount>
      </li>
    </skillGains>
    <spawnCategories>
      <li>FennexBackstory</li>
    </spawnCategories>
  </AlienRace.BackstoryDef>

  	  <AlienRace.BackstoryDef>
    <defName>FennexMathman</defName>
    <title>Mathematician</title>
    <titleShort>Mathematician</titleShort>
    <baseDescription>[PAWN_nameDef] is a professional mathematician. [PAWN_pronoun] uses [PAWN_possessive] expertise with mathematics to solve difficult engineering and physics problems.</baseDescription>
    <bodyTypeMale>Male</bodyTypeMale>
    <bodyTypeFemale>Female</bodyTypeFemale>
    <bodyTypeGlobal>Thin</bodyTypeGlobal>
		<maleCommonality>8</maleCommonality>
	<femaleCommonality>8</femaleCommonality>
    <slot>Adulthood</slot>
    <skillGains>
      <li>
        <defName>Shooting</defName>
        <amount>2</amount>
      </li>
	   <li>
        <defName>Social</defName>
        <amount>2</amount>
      </li>
      <li>
        <defName>Intellectual</defName>
        <amount>6</amount>
      </li>
    </skillGains>
    <spawnCategories>
      <li>FennexBackstory</li>
    </spawnCategories>
  </AlienRace.BackstoryDef>


      <AlienRace.BackstoryDef>
    <defName>FennexAirMech</defName>
    <title>Airfield mechanic</title>
    <titleShort>Air-mechanic</titleShort>
    <baseDescription>[PAWN_nameDef] was a skilled mechanic, in charge of maintenance at a major airfield. [PAWN_pronoun] was hard-pressed to keep up with the workload, but [PAWN_possessive] team was competant, and helped keep the airfield and it's traffic in good working order.</baseDescription>
		<bodyTypeMale>Male</bodyTypeMale>
    <bodyTypeFemale>Female</bodyTypeFemale>
    <maleCommonality>25</maleCommonality>
	<femaleCommonality>25</femaleCommonality>
    <slot>Adulthood</slot>
    <skillGains>
      <li>
        <defName>Shooting</defName>
        <amount>5</amount>
      </li>
	  <li>
        <defName>Crafting</defName>
        <amount>5</amount>
      </li>
	  	<li>
        <defName>Intellectual</defName>
        <amount>5</amount>
      </li>
    </skillGains>
    <spawnCategories>
      <li>FennexBackstory</li>
    </spawnCategories>
  </AlienRace.BackstoryDef>

    <AlienRace.BackstoryDef>
    <defName>FennexPlanetol</defName>
    <title>Exoplanetologist</title>
    <titleShort>Exoplanetologist</titleShort>
    <baseDescription>[PAWN_nameDef] is a scientist specializing in studying planets that orbit a star outside the current stellar system. [PAWN_pronoun] has developed a special set of skills, software, and tools, for studying distant planets to uncover potential resources or discoveries.</baseDescription>
		<maleCommonality>30</maleCommonality>
	<femaleCommonality>30</femaleCommonality>
    <bodyTypeMale>Thin</bodyTypeMale>
    <bodyTypeFemale>Thin</bodyTypeFemale>
    <slot>Adulthood</slot>
    <skillGains>
      <li>
        <defName>Shooting</defName>
        <amount>6</amount>
      </li>
	  <li>
        <defName>Intellectual</defName>
        <amount>4</amount>
      </li>
    </skillGains>
    <spawnCategories>
      <li>FennexBackstory</li>
    </spawnCategories>
  </AlienRace.BackstoryDef>

</Defs>
